{
  "date": "July 25-30, 2016",
  "medium": "Digital Photography",
  "folder": "gallery-venezia",
  "gallery-page": {
    "works": [
      {
        "imgTitle": "Amanda and I arrive in Venice, first selfie",
        "imgFile": "venezia-01",
        "location": "Ponte degli Scalzi, Venice, Italy",
        "camera": "Apple iPhone 6",
        "description": "Our honeymoon adventure begins. Here we are crying on the Ponte degli Scalzi bridge right after we arrived in Venice and had been traveling for almost 24 hours."
      },
      {
        "imgTitle": "Ca' San Giorgio, our hotel",
        "imgFile": "venezia-02",
        "location": "Ca' San Giorgio, Venice, Italy",
        "camera": "Panasonic Lumix DMC-GF1",
        "lens": "Panasonic 7-14mm f/4.0",
        "description": "The bed and breakfast where we stayed in Venice."
      },
      {
        "imgTitle": "",
        "imgFile": "venezia-03",
        "location": "Venice, Italy",
        "camera": "",
        "lens": "",
        "description": "Coming soon"
      },
      {
        "imgTitle": "",
        "imgFile": "venezia-04",
        "location": "Venice, Italy",
        "camera": "",
        "lens": "",
        "description": "Coming soon"
      },
      {
        "imgTitle": "",
        "imgFile": "venezia-05",
        "location": "Venice, Italy",
        "camera": "",
        "lens": "",
        "description": "Coming soon"
      },
      {
        "imgTitle": "",
        "imgFile": "venezia-06",
        "location": "Venice, Italy",
        "camera": "",
        "lens": "",
        "description": "Coming soon"
      },
      {
        "imgTitle": "",
        "imgFile": "venezia-07",
        "location": "Venice, Italy",
        "camera": "",
        "lens": "",
        "description": "Coming soon"
      },
      {
        "imgTitle": "",
        "imgFile": "venezia-08",
        "location": "Venice, Italy",
        "camera": "",
        "lens": "",
        "description": "Coming soon"
      },
      {
        "imgTitle": "",
        "imgFile": "venezia-09",
        "location": "Venice, Italy",
        "camera": "",
        "lens": "",
        "description": "Coming soon"
      },
      {
        "imgTitle": "",
        "imgFile": "venezia-10",
        "location": "Venice, Italy",
        "camera": "",
        "lens": "",
        "description": "Coming soon"
      },
      {
        "imgTitle": "",
        "imgFile": "venezia-11",
        "location": "Venice, Italy",
        "camera": "",
        "lens": "",
        "description": "Coming soon"
      },
      {
        "imgTitle": "",
        "imgFile": "venezia-12",
        "location": "Venice, Italy",
        "camera": "",
        "lens": "",
        "description": "Coming soon"
      },
      {
        "imgTitle": "",
        "imgFile": "venezia-13",
        "location": "Venice, Italy",
        "camera": "",
        "lens": "",
        "description": "Coming soon"
      },
      {
        "imgTitle": "",
        "imgFile": "venezia-14",
        "location": "Venice, Italy",
        "camera": "",
        "lens": "",
        "description": "Coming soon"
      },
      {
        "imgTitle": "",
        "imgFile": "venezia-15",
        "location": "Venice, Italy",
        "camera": "",
        "lens": "",
        "description": "Coming soon"
      },
      {
        "imgTitle": "",
        "imgFile": "venezia-16",
        "location": "Venice, Italy",
        "camera": "",
        "lens": "",
        "description": "Coming soon"
      },
      {
        "imgTitle": "",
        "imgFile": "venezia-17",
        "location": "Venice, Italy",
        "camera": "",
        "lens": "",
        "description": "Coming soon"
      },
      {
        "imgTitle": "",
        "imgFile": "venezia-18",
        "location": "Venice, Italy",
        "camera": "",
        "lens": "",
        "description": "Coming soon"
      },
      {
        "imgTitle": "",
        "imgFile": "venezia-19",
        "location": "Venice, Italy",
        "camera": "",
        "lens": "",
        "description": "Coming soon"
      },
      {
        "imgTitle": "",
        "imgFile": "venezia-20",
        "location": "Venice, Italy",
        "camera": "",
        "lens": "",
        "description": "Coming soon"
      },
      {
        "imgTitle": "",
        "imgFile": "venezia-21",
        "location": "Venice, Italy",
        "camera": "",
        "lens": "",
        "description": "Coming soon"
      },
      {
        "imgTitle": "",
        "imgFile": "venezia-22",
        "location": "Venice, Italy",
        "camera": "",
        "lens": "",
        "description": "Coming soon"
      },
      {
        "imgTitle": "",
        "imgFile": "venezia-23",
        "location": "Venice, Italy",
        "camera": "",
        "lens": "",
        "description": "Coming soon"
      },
      {
        "imgTitle": "",
        "imgFile": "venezia-24",
        "location": "Venice, Italy",
        "camera": "",
        "lens": "",
        "description": "Coming soon"
      },
      {
        "imgTitle": "",
        "imgFile": "venezia-25",
        "location": "Venice, Italy",
        "camera": "",
        "lens": "",
        "description": "Coming soon"
      },
      {
        "imgTitle": "",
        "imgFile": "venezia-26",
        "location": "Venice, Italy",
        "camera": "",
        "lens": "",
        "description": "Coming soon"
      },
      {
        "imgTitle": "",
        "imgFile": "venezia-27",
        "location": "Venice, Italy",
        "camera": "",
        "lens": "",
        "description": "Coming soon"
      },
      {
        "imgTitle": "",
        "imgFile": "venezia-28",
        "location": "Venice, Italy",
        "camera": "",
        "lens": "",
        "description": "Coming soon"
      },
      {
        "imgTitle": "",
        "imgFile": "venezia-29",
        "location": "Venice, Italy",
        "camera": "",
        "lens": "",
        "description": "Coming soon"
      },
      {
        "imgTitle": "",
        "imgFile": "venezia-30",
        "location": "Venice, Italy",
        "camera": "",
        "lens": "",
        "description": "Coming soon"
      },
      {
        "imgTitle": "",
        "imgFile": "venezia-31",
        "location": "Venice, Italy",
        "camera": "",
        "lens": "",
        "description": "Coming soon"
      },
      {
        "imgTitle": "",
        "imgFile": "venezia-32",
        "location": "Venice, Italy",
        "camera": "",
        "lens": "",
        "description": "Coming soon"
      },
      {
        "imgTitle": "",
        "imgFile": "venezia-33",
        "location": "Venice, Italy",
        "camera": "",
        "lens": "",
        "description": "Coming soon"
      },
      {
        "imgTitle": "",
        "imgFile": "venezia-34",
        "location": "Venice, Italy",
        "camera": "",
        "lens": "",
        "description": "Coming soon"
      },
      {
        "imgTitle": "2016 vs 2010 Comparison: Cannaregio Campaniello",
        "imgFile": "venezia-35",
        "location": "Cannaregio, Venice, Italy",
        "camera": "Panasonic Lumix DMC-GF1 (top) and Panasonic Lumix DMC-G1 (bottom)",
        "description": "Coming soon"
      },
      {
        "imgTitle": "",
        "imgFile": "venezia-36",
        "location": "Venice, Italy",
        "camera": "",
        "lens": "",
        "description": "Coming soon"
      },
      {
        "imgTitle": "",
        "imgFile": "venezia-37",
        "location": "Venice, Italy",
        "camera": "",
        "lens": "",
        "description": "Coming soon"
      },
      {
        "imgTitle": "",
        "imgFile": "venezia-38",
        "location": "Venice, Italy",
        "camera": "",
        "lens": "",
        "description": "Coming soon"
      },
      {
        "imgTitle": "",
        "imgFile": "venezia-39",
        "location": "Venice, Italy",
        "camera": "",
        "lens": "",
        "description": "Coming soon"
      },
      {
        "imgTitle": "",
        "imgFile": "venezia-40",
        "location": "Venice, Italy",
        "camera": "",
        "lens": "",
        "description": "Coming soon"
      },
      {
        "imgTitle": "",
        "imgFile": "venezia-41",
        "location": "Venice, Italy",
        "camera": "",
        "lens": "",
        "description": "Coming soon"
      },
      {
        "imgTitle": "",
        "imgFile": "venezia-42",
        "location": "Venice, Italy",
        "camera": "",
        "lens": "",
        "description": "Coming soon"
      },
      {
        "imgTitle": "",
        "imgFile": "venezia-43",
        "location": "Venice, Italy",
        "camera": "",
        "lens": "",
        "description": "Coming soon"
      },
      {
        "imgTitle": "",
        "imgFile": "venezia-44",
        "location": "Venice, Italy",
        "camera": "",
        "lens": "",
        "description": "Coming soon"
      },
      {
        "imgTitle": "",
        "imgFile": "venezia-45",
        "location": "Venice, Italy",
        "camera": "",
        "lens": "",
        "description": "Coming soon"
      },
      {
        "imgTitle": "",
        "imgFile": "venezia-46",
        "location": "Venice, Italy",
        "camera": "",
        "lens": "",
        "description": "Coming soon"
      },
      {
        "imgTitle": "",
        "imgFile": "venezia-47",
        "location": "Venice, Italy",
        "camera": "",
        "lens": "",
        "description": "Coming soon"
      },
      {
        "imgTitle": "",
        "imgFile": "venezia-48",
        "location": "Venice, Italy",
        "camera": "",
        "lens": "",
        "description": "Coming soon"
      },
      {
        "imgTitle": "",
        "imgFile": "venezia-49",
        "location": "Venice, Italy",
        "camera": "",
        "lens": "",
        "description": "Coming soon"
      },
      {
        "imgTitle": "",
        "imgFile": "venezia-50",
        "location": "Venice, Italy",
        "camera": "",
        "lens": "",
        "description": "Coming soon"
      }
    ]
  },
  "pagenav": {
    "type": "photos",
    "id": "venezia"
  }
}